DESCRIPTION.rst
MANIFEST.in
setup.cfg
setup.py
zensend/__init__.py
zensend.egg-info/PKG-INFO
zensend.egg-info/SOURCES.txt
zensend.egg-info/dependency_links.txt
zensend.egg-info/requires.txt
zensend.egg-info/top_level.txt