Metadata-Version: 1.1
Name: zensend
Version: 1.2.0
Summary: ZenSend python bindings
Home-page: https://github.com/fonixcode/zensend_python_api
Author: ZenSend
Author-email: tech@fonix.io
License: MIT
Keywords: sms
Platform: UNKNOWN
Classifier: Development Status :: 3 - Alpha
Classifier: Intended Audience :: Developers
Classifier: Topic :: Software Development :: Libraries :: Python Modules
Classifier: License :: OSI Approved :: MIT License
Classifier: Programming Language :: Python :: 2
Classifier: Programming Language :: Python :: 2.6
Classifier: Programming Language :: Python :: 2.7
Classifier: Programming Language :: Python :: 3
Classifier: Programming Language :: Python :: 3.2
Classifier: Programming Language :: Python :: 3.3
Classifier: Programming Language :: Python :: 3.4
